data/__init__.py
data/analysis/__init__.py
data/analysis/information/__init__.py
data/analysis/information/extract/__init__.py
data/analysis/information/extract/jms/__init__.py
data/analysis/information/extract/jms/information_extract_tool.py
data_analysis_information_extract_jms-0.0.1.dist-info/LICENSE
data_analysis_information_extract_jms-0.0.1.dist-info/METADATA
data_analysis_information_extract_jms-0.0.1.dist-info/WHEEL
data_analysis_information_extract_jms-0.0.1.dist-info/top_level.txt
data_analysis_information_extract_jms-0.0.1.dist-info/RECORD
