Metadata-Version: 2.1
Name: data-analysis-information-extract-jms
Version: 0.0.1
Summary: A data processor package
Home-page: https://github.com/Jane-Dream/data-analysis-information-extract-jms
Author: Jane-Dream
Author-email: janedream515@gmail.com
Project-URL: Source, https://github.com/Jane-Dream/data-analysis-information-extract-jms
Classifier: Programming Language :: Python :: 3
Classifier: License :: OSI Approved :: MIT License
Classifier: Operating System :: OS Independent
Requires-Python: >=3.6
License-File: LICENSE
Requires-Dist: requests >=2.24.0
Requires-Dist: setuptools >=42
Requires-Dist: numpy >=1.24.4
Requires-Dist: data-analysis-tools-fdx >=0.0.1
Requires-Dist: data-analysis-tools-jms-diy >=0.0.1
Requires-Dist: data-analysis-tools-alpha >=0.0.1
Requires-Dist: data-analysis-tools-bet >=0.0.1
Requires-Dist: data-analysis-tools-cat >=0.0.1
Requires-Dist: data-analysis-tools-dog >=0.0.1
Requires-Dist: data-analysis-tools-eth >=0.0.1
Requires-Dist: paddlenlp >=2.6.1
